Metadata-Version: 2.1
Name: regressionmodels
Version: 0.0.1
Summary: Gaussian distributions
Home-page: UNKNOWN
License: UNKNOWN
Platform: UNKNOWN
Provides-Extra: dev
